LICENSE
MANIFEST.in
README.rst
setup.py
django_seeding_data.egg-info/PKG-INFO
django_seeding_data.egg-info/SOURCES.txt
django_seeding_data.egg-info/dependency_links.txt
django_seeding_data.egg-info/top_level.txt
seeding/__init__.py
seeding/apps.py
seeding/models.py
seeding/tests.py
seeding/management/__init__.py
seeding/management/commands/__init__.py
seeding/management/commands/seeding.py
seeding/migrations/0001_initial.py
seeding/migrations/0002_alter_seeding_applied.py
seeding/migrations/__init__.py
seeding/seeding/__init__.py